<?xml version="1.0" encoding="UTF-8"?>
<portlet-app xmlns="http://java.sun.com/xml/ns/portlet/portlet-app_2_0.xsd"
             version="2.0"
             xmlns:xsi="http://www.w3.org/2001/XMLSchema-instance"
             xsi:schemaLocation="http://java.sun.com/xml/ns/portlet/portlet-app_2_0.xsd
   http://java.sun.com/xml/ns/portlet/portlet-app_2_0.xsd">
   <portlet>
     <portlet-name>SpacePortlet</portlet-name>
     <display-name xml:lang="EN">Space Application</display-name>
     <portlet-class>org.social.portlet.PortletPortlet</portlet-class>
     <init-param>
       <name>juzu.run_mode</name>
       <value>dev</value>
     </init-param>
     <init-param>
       <name>juzu.src_path</name>
       <value>/home/hanhvq/java/eXoProjects/others/space-portlet/src/main/java</value>
     </init-param>
     <init-param>
       <name>juzu.inject</name>
       <value>weld</value>
     </init-param>
     <supports>
       <mime-type>text/html</mime-type>
     </supports>
     <portlet-info>
       <title>Space Portlet</title>
     </portlet-info>
   </portlet>
</portlet-app>
